{
  "query": "MSI PRO B650M-P",
  "searchUrl": "https://search.danawa.com/dsearch.php?query=MSI+PRO+B650M-P",
  "capturedAt": "2026-05-23T11:12:39.251Z",
  "searchHttpStatus": 200,
  "searchHtmlHash": "3a6d759a1ccb2abca1ff2566d6427a9cbe8dd0a29a3e436d96b3948985424d11",
  "resultCount": 1,
  "results": [
    {
      "pcode": "20108249",
      "name": "MSI PRO B650M-P",
      "productUrl": "https://prod.danawa.com/info/?pcode=20108249&keyword=MSI+PRO+B650M-P&cate=112751",
      "imageUrl": "https://img.danuri.io/catalog-image/249/108/020/f147732d496c4e25aafe1f83f79db9a8.jpg",
      "price": 116820,
      "cate": "112751",
      "variants": [],
      "source": "search_dom",
      "detail": {
        "httpStatus": 200,
        "htmlHash": "e892e8bb8565dbc1b8024f58ea5b858b246316b7ae05e9ac91e0f99f5475c38c",
        "metadata": {
          "pcode": "20108249",
          "categoryCode": "112751",
          "category1": "861",
          "category2": "875",
          "category3": "969",
          "category4": "0",
          "productFullName": "MSI PRO B650M-P",
          "makerName": "MSI",
          "brandName": "PRO",
          "makerUrl": "http://kr.msi.com",
          "kccode": "R-R-MSI-10-7E27",
          "kpscode": "",
          "circulName": "",
          "productName": "B650M-P",
          "prodType": "T1",
          "displayMakeDate": "2023.05.",
          "productUrl": "https://prod.danawa.com/info/?pcode=20108249&keyword=MSI+PRO+B650M-P&cate=112751"
        },
        "descriptionHttpStatus": 200,
        "descriptionHtmlHash": "919ed338c2d99cbdafa540252e0a368f70c099be9a5cfa9c75715eaf14ddeefc",
        "specs": [
          {
            "section": null,
            "key": "제조회사",
            "value": "MSI (제조사 웹사이트 바로가기)"
          },
          {
            "section": null,
            "key": "등록년월",
            "value": "2023년 05월"
          },
          {
            "section": "기본 사양",
            "key": "제품 분류",
            "value": "AMD CPU용"
          },
          {
            "section": "기본 사양",
            "key": "CPU 소켓",
            "value": "AMD(소켓AM5)"
          },
          {
            "section": "기본 사양",
            "key": "세부 칩셋",
            "value": "AMD B650"
          },
          {
            "section": "기본 사양",
            "key": "메모리 종류",
            "value": "DDR5"
          },
          {
            "section": "기본 사양",
            "key": "VGA 연결",
            "value": "PCIe4.0 x16"
          },
          {
            "section": "기본 사양",
            "key": "폼팩터",
            "value": "M-ATX (24.4x24.4cm)"
          },
          {
            "section": "기본 사양",
            "key": "CPU 장착수",
            "value": "1개"
          },
          {
            "section": "기본 사양",
            "key": "전원부",
            "value": "9페이즈"
          },
          {
            "section": "[메모리]",
            "key": "메모리 속도",
            "value": "7200MHz (PC5-57600)"
          },
          {
            "section": "[메모리]",
            "key": "메모리 슬롯",
            "value": "4개"
          },
          {
            "section": "[메모리]",
            "key": "메모리 채널",
            "value": "듀얼"
          },
          {
            "section": "[메모리]",
            "key": "메모리 용량",
            "value": "최대 256GB"
          },
          {
            "section": "메모리 기술",
            "key": "EXPO",
            "value": "○"
          },
          {
            "section": "PCIe버전",
            "key": "PCIe4.0",
            "value": "○"
          },
          {
            "section": "PCIe버전",
            "key": "PCIe3.0",
            "value": "○"
          },
          {
            "section": "PCIe슬롯",
            "key": "PCIex1",
            "value": "2개"
          },
          {
            "section": "[저장장치]",
            "key": "M.2",
            "value": "2개"
          },
          {
            "section": "[저장장치]",
            "key": "SATA3",
            "value": "4개"
          },
          {
            "section": "M.2 연결",
            "key": "PCIe4.0",
            "value": "○"
          },
          {
            "section": "M.2 연결",
            "key": "NVMe",
            "value": "○"
          },
          {
            "section": "M.2 폼팩터",
            "key": "2260",
            "value": "○"
          },
          {
            "section": "M.2 폼팩터",
            "key": "2280",
            "value": "○"
          },
          {
            "section": "RAID 지원",
            "key": "NVMe RAID",
            "value": "○"
          },
          {
            "section": "RAID 지원",
            "key": "SATA RAID",
            "value": "○"
          },
          {
            "section": "그래픽 출력",
            "key": "HDMI",
            "value": "○"
          },
          {
            "section": "그래픽 출력",
            "key": "DP",
            "value": "○"
          },
          {
            "section": "그래픽 출력",
            "key": "D-SUB",
            "value": "○"
          },
          {
            "section": "후면단자",
            "key": "USB3.x 10Gbps",
            "value": "○"
          },
          {
            "section": "후면단자",
            "key": "USB3.x 5Gbps",
            "value": "○"
          },
          {
            "section": "후면단자",
            "key": "USB 2.0",
            "value": "○"
          },
          {
            "section": "후면단자",
            "key": "RJ-45",
            "value": "○"
          },
          {
            "section": "후면단자",
            "key": "오디오잭",
            "value": "○"
          },
          {
            "section": "후면단자",
            "key": "PS/2",
            "value": "○"
          },
          {
            "section": "후면단자",
            "key": "USB A타입",
            "value": "8개"
          },
          {
            "section": "후면단자",
            "key": "USB A타입 10Gbps",
            "value": "후면 2개"
          },
          {
            "section": "후면단자",
            "key": "USB A타입 5Gbps",
            "value": "후면 2개"
          },
          {
            "section": "후면단자",
            "key": "USB2.0",
            "value": "후면 4개"
          },
          {
            "section": "네트워크",
            "key": "유선랜 칩셋",
            "value": "Realtek RTL8125B"
          },
          {
            "section": "네트워크",
            "key": "유선랜 속도",
            "value": "2.5Gbps"
          },
          {
            "section": "네트워크",
            "key": "RJ-45",
            "value": "1개"
          },
          {
            "section": "오디오",
            "key": "오디오 칩셋",
            "value": "Realtek ALC897"
          },
          {
            "section": "오디오",
            "key": "아날로그 출력",
            "value": "7.1채널(8ch)"
          },
          {
            "section": "USB/팬 헤더",
            "key": "USB3.0 헤더",
            "value": "○"
          },
          {
            "section": "USB/팬 헤더",
            "key": "USB2.0 헤더",
            "value": "○"
          },
          {
            "section": "USB/팬 헤더",
            "key": "USB3.1 Type C 헤더",
            "value": "○"
          },
          {
            "section": "USB/팬 헤더",
            "key": "RGB 12V 4핀 헤더",
            "value": "○"
          },
          {
            "section": "USB/팬 헤더",
            "key": "ARGB 5V 3핀 헤더",
            "value": "○"
          },
          {
            "section": "USB/팬 헤더",
            "key": "펌프전용 헤더",
            "value": "○"
          },
          {
            "section": "USB/팬 헤더",
            "key": "RGB 4핀",
            "value": "2개"
          },
          {
            "section": "USB/팬 헤더",
            "key": "ARGB 3핀",
            "value": "2개"
          },
          {
            "section": "USB/팬 헤더",
            "key": "시스템팬 4핀",
            "value": "3개"
          },
          {
            "section": "USB/팬 헤더",
            "key": "USB2.0 헤더",
            "value": "2개"
          },
          {
            "section": "USB/팬 헤더",
            "key": "USB3.0 헤더",
            "value": "1개"
          },
          {
            "section": "USB/팬 헤더",
            "key": "USB3.1 C타입 헤더",
            "value": "1개"
          },
          {
            "section": "특징",
            "key": "전원부 방열판",
            "value": "○"
          },
          {
            "section": "특징",
            "key": "UEFI",
            "value": "○"
          },
          {
            "section": "KC인증",
            "key": "적합성평가인증",
            "value": "R-R-MSI-10-7E27 인증번호 확인"
          },
          {
            "section": "KC인증",
            "key": "안전확인인증",
            "value": "상세설명 / 판매 사이트 문의 인증번호 확인"
          }
        ]
      }
    }
  ]
}